{
  "id": "dmhub-integration",
  "name": "dmhub-integration",
  "title": "DMHUB Integration",
  "description": "Integração entre DMHUB e Foundry VTT para sincronização de campanhas e personagens",
  "version": "1.0.0",
  "author": "Rufino-BR",
  "minimumCoreVersion": "13",
  "compatibleCoreVersion": "13",
  "url": "https://github.com/Rufino-BR/dmhub-integration",
  "manifest": "https://raw.githubusercontent.com/Rufino-BR/dmhub-integration/main/module.json",
  "download": "https://github.com/Rufino-BR/dmhub-integration/releases/latest/download/dmhub-integration.zip",
  "esmodules": [
    "scripts/dmhub-api.js",
    "scripts/dmhub-config.js"
  ],
  "styles": [
    "styles/dmhub.css"
  ],
  "socket": true,
  "protected": false,
  "coreTranslation": false,
  "library": false
}
